latextranslator/__init__.py
latextranslator/__main__.py
latextranslator/basura.py
latextranslator/main.py
latextranslator/translations.py
latextranslator/translator.py
latextranslator/blindtex/__init__.py
latextranslator/blindtex/mainBlindtex.py
latextranslator/blindtex/tex2all.py
latextranslator/blindtex/interpreter/__init__.py
latextranslator/blindtex/interpreter/dictionary.py
latextranslator/blindtex/interpreter/reader.py
latextranslator/blindtex/iotools/__init__.py
latextranslator/blindtex/iotools/file.py
latextranslator/blindtex/iotools/iotools.py
latextranslator/blindtex/iotools/stringtools.py
latextranslator/blindtex/lang/__init__.py
latextranslator/blindtex/lang/translator.py
latextranslator/blindtex/lang/dicts/Accents.json
latextranslator/blindtex/lang/dicts/Arrows.json
latextranslator/blindtex/lang/dicts/BinaryOperators.json
latextranslator/blindtex/lang/dicts/BinaryRelations.json
latextranslator/blindtex/lang/dicts/Delimiters.json
latextranslator/blindtex/lang/dicts/Dots.json
latextranslator/blindtex/lang/dicts/LargeOperators.json
latextranslator/blindtex/lang/dicts/MathFunctions.json
latextranslator/blindtex/lang/dicts/Ordinary.json
latextranslator/blindtex/lang/dicts/Styles.json
latextranslator/blindtex/lang/dicts/UserDict.json
latextranslator/blindtex/lang/dicts/regexes.json
latextranslator/blindtex/lang/dicts/spanish.json
latextranslator/blindtex/lang/dicts/spanish.yaml
latextranslator/blindtex/latex2ast/__init__.py
latextranslator/blindtex/latex2ast/converter.py
latextranslator/blindtex/latex2ast/lexer.py
latextranslator/blindtex/latex2ast/math_object.py
latextranslator/blindtex/latex2ast/parser.out
latextranslator/blindtex/latex2ast/parser.py
latextranslator/blindtex/latex2ast/parsetab.py
latextranslator-0.1.1.dist-info/entry_points.txt
latextranslator-0.1.1.dist-info/LICENSE
latextranslator-0.1.1.dist-info/WHEEL
latextranslator-0.1.1.dist-info/METADATA
latextranslator-0.1.1.dist-info/RECORD
