Metadata-Version: 2.1
Name: latextranslator
Version: 0.1.1
Summary: A LaTeX to TXT file translator.
Author-email: Bruno Prieto <brunoprietog@hey.com>
Requires-Python: >=3.7
Classifier: License :: OSI Approved :: MIT License
Requires-Dist: click
Requires-Dist: ply
Requires-Dist: pytest ; extra == "test"
Project-URL: Home, https://github.com/brunoprietog/latextranslator
Provides-Extra: test
